caf/viz/__init__.py
caf/viz/_version.py
caf/viz/py.typed
caf/viz/subplots.py
caf/viz/utils.py
caf/viz/xy_plot.py
caf.viz-0.1.1.dist-info/LICENSE
caf.viz-0.1.1.dist-info/METADATA
caf.viz-0.1.1.dist-info/WHEEL
caf.viz-0.1.1.dist-info/top_level.txt
caf.viz-0.1.1.dist-info/RECORD
