Metadata-Version: 2.1
Name: caf.viz
Version: 0.1.1
Summary: Python-based visualisation tools for transport data
Author: Transport for the North
License: Copyright © Transport for the North (“TfN”) (2024).
Project-URL: Bug Tracker, https://github.com/Transport-for-the-North/caf.viz/issues
Project-URL: Homepage, https://github.com/Transport-for-the-North/caf.viz
Project-URL: Source, https://github.com/Transport-for-the-North/caf.viz
Classifier: Programming Language :: Python :: 3 :: Only
Classifier: Programming Language :: Python :: 3.10
Classifier: Programming Language :: Python :: 3.11
Classifier: Programming Language :: Python :: 3.12
Requires-Python: >=3.10
License-File: LICENSE
Requires-Dist: numpy >=1.19.0
Requires-Dist: pandas >=1.4.0
Requires-Dist: matplotlib >=3.8.2
Requires-Dist: scipy >=1.11.4
Requires-Dist: pydantic >=2.0
Provides-Extra: lint
Requires-Dist: black >=22.6.0 ; extra == 'lint'
Requires-Dist: isort >=5.12.0 ; extra == 'lint'
Requires-Dist: mypy >=1.0.0 ; extra == 'lint'
Requires-Dist: mypy-extensions >=1.0.0 ; extra == 'lint'
Requires-Dist: pydocstyle[toml] >=6.1.1 ; extra == 'lint'
Requires-Dist: pylint >=2.14.5 ; extra == 'lint'
Provides-Extra: test
Requires-Dist: pytest >=7.4.0 ; extra == 'test'
Requires-Dist: pytest-cov >=4.1.0 ; extra == 'test'
Requires-Dist: pytest-xdist >=3.3.1 ; extra == 'test'
